collpay/__init__.py
collpay/api.py
dk_test_py2-0.0.14.dist-info/LICENSE
dk_test_py2-0.0.14.dist-info/METADATA
dk_test_py2-0.0.14.dist-info/WHEEL
dk_test_py2-0.0.14.dist-info/top_level.txt
dk_test_py2-0.0.14.dist-info/RECORD
