Metadata-Version: 2.1
Name: dk-test-py2
Version: 0.0.14
Summary: A small example package
Home-page: https://github.com/Dip1059/python-test-pkg
Author: Example Author
Author-email: author@example.com
License: UNKNOWN
Platform: UNKNOWN
Classifier: Programming Language :: Python :: 3
Classifier: License :: OSI Approved :: MIT License
Classifier: Operating System :: OS Independent
Requires-Python: >=3.6
Requires-Dist: requests (>=2.22.0)
